{
    "aboutGwp": {
        "title": "About the Great White Project",
        "heading": "Tracking Great Whites in New Zealand",
        "sections": [
            {
                "type": "image",
                "src": "/assets/images/aboutGwpHeader.jpg",
                "alt": "Photo of Riley diving with great white shark"
            },
            {
                "type": "text",
                "content": "The Great White Project led by Dr Riley Elliott focuses on the presence of Great White sharks in New Zealand - their habitat use, their behaviour, overlap with fisheries and the recreation of people in the ocean. It started with a novel and emerging population of baby and juvenile Great Whites in northeast NZ, but has now grown to tag sub-adult and mature Great Whites in a world famous aggregation site in southern NZ - Stewart Island."
            },
            {
                "type": "text",
                "content": "No tagging and monitoring of Great Whites has occurred in Stewart Island since 2015. In May 2025 The Great White App and tags sponsored by the NZ public, began to fill a decade-old black hole of understanding."
            },
            {
                "type": "text",
                "content": "16 satellite tags are deployed on a range of sexes and ages, to track anywhere in the world these animals may roam. The project aim is not just to entertain you with live tracks, but also to generate scientific data that allows insight to migration routes, predator prey relationships, genetic links to Australia, population estimates in collaboration with Australia, and overall monitoring of habitat use by this protected species."
            },
            {
                "type": "button",
                "buttonText": "Scroll to Top",
                "onClick": "scrollToTop"
            }
        ]
    },
    "usingGwa": {
        "title": "Using the Great White App",
        "heading": "Interacting with The Great White App",
        "sections": [
            {
                "type": "text",
                "content": "This section is coming soon! The content needs to be written first..."
            }
        ]
    },
    "commonQuestions": {
        "title": "Frequently Asked Questions",
        "heading": "Answers to your questions",
        "sections": [
            {
                "type": "text",
                "content": "FAQ to be added."
            }
        ]
    },
    "bugReport": {
        "title": "Report an Issue",
        "heading": "Something wrong? Let us know.",
        "sections": [
            {
                "type": "text",
                "content": "FAQ to be added."
            }
        ]
    }
}